infopy/__init__.py
infopy/estimators.py
infopy/functional.py
infopy_estimators-0.1.3.dist-info/METADATA
infopy_estimators-0.1.3.dist-info/WHEEL
infopy_estimators-0.1.3.dist-info/licenses/LICENSE
infopy_estimators-0.1.3.dist-info/RECORD
