Metadata-Version: 2.4
Name: infopy-estimators
Version: 0.1.3
Summary: Information theory related estimators
Project-URL: Homepage, https://github.com/jurrutiag/infopy
Project-URL: Repository, https://github.com/jurrutiag/infopy
Author-email: Juan Urrutia <juan.urrutia.gandolfo@gmail.com>
License: MIT
License-File: LICENSE
Classifier: Operating System :: Microsoft :: Windows
Classifier: Operating System :: POSIX
Classifier: Operating System :: Unix
Classifier: Programming Language :: Python
Classifier: Programming Language :: Python :: 3.9
Classifier: Programming Language :: Python :: 3.10
Classifier: Programming Language :: Python :: 3.11
Classifier: Programming Language :: Python :: 3.12
Requires-Python: >=3.9
Requires-Dist: numpy
Requires-Dist: scikit-learn
Requires-Dist: scipy
Provides-Extra: testing
Requires-Dist: pytest-cov>=6.2.1; extra == 'testing'
Requires-Dist: pytest>=8.4.1; extra == 'testing'
